Metadata-Version: 1.0
Name: django-celery-transactions
Version: 0.1.1
Summary: Django transaction support for Celery tasks.
Home-page: https://github.com/chrisdoble/django-celery-transactions
Author: Chris Doble
Author-email: chris@chrisdoble.com
License: Simplified BSD
Platform: UNKNOWN
Classifier: Framework :: Django
Classifier: Intended Audience :: Developers
Classifier: License :: OSI Approved :: BSD License
Classifier: Operating System :: OS Independent
Classifier: Programming Language :: Python
Classifier: Topic :: Database
